docmerge/__init__.py
docmerge/__version__.py
docmerge/decorator.py
docmerge/merger.py
docmerge/misc.py
docmerge-1.0.0.dist-info/LICENSE
docmerge-1.0.0.dist-info/METADATA
docmerge-1.0.0.dist-info/WHEEL
docmerge-1.0.0.dist-info/top_level.txt
docmerge-1.0.0.dist-info/zip-safe
docmerge-1.0.0.dist-info/RECORD
